hikyuu_plugin/__init__.py
hikyuu_plugin/extra.py
hikyuu_plugin/libbacktest.dylib
hikyuu_plugin/libboost_atomic.1.90.0.dylib
hikyuu_plugin/libboost_atomic.dylib
hikyuu_plugin/libboost_charconv.1.90.0.dylib
hikyuu_plugin/libboost_charconv.dylib
hikyuu_plugin/libboost_chrono.1.90.0.dylib
hikyuu_plugin/libboost_chrono.dylib
hikyuu_plugin/libboost_container.1.90.0.dylib
hikyuu_plugin/libboost_container.dylib
hikyuu_plugin/libboost_date_time.1.90.0.dylib
hikyuu_plugin/libboost_date_time.dylib
hikyuu_plugin/libboost_locale.1.90.0.dylib
hikyuu_plugin/libboost_locale.dylib
hikyuu_plugin/libboost_random.1.90.0.dylib
hikyuu_plugin/libboost_random.dylib
hikyuu_plugin/libboost_serialization.1.90.0.dylib
hikyuu_plugin/libboost_serialization.dylib
hikyuu_plugin/libboost_thread.1.90.0.dylib
hikyuu_plugin/libboost_thread.dylib
hikyuu_plugin/libboost_wserialization.1.90.0.dylib
hikyuu_plugin/libboost_wserialization.dylib
hikyuu_plugin/libcheckdata.dylib
hikyuu_plugin/libclickhousedriver.dylib
hikyuu_plugin/libdataserver.dylib
hikyuu_plugin/libdataserver_parquet.dylib
hikyuu_plugin/libdevice.dylib
hikyuu_plugin/libextind.dylib
hikyuu_plugin/libhkuextra.dylib
hikyuu_plugin/libimport2ch.dylib
hikyuu_plugin/libimport2hdf5.dylib
hikyuu_plugin/libimport2mysql.dylib
hikyuu_plugin/libtmreport.dylib
hikyuu_plugin/pycheck.so
hikyuu_plugin/pycheck310.so
hikyuu_plugin/pycheck311.so
hikyuu_plugin/pycheck312.so
hikyuu_plugin/pycheck313.so
hikyuu_plugin/pyextra.so
hikyuu_plugin/pyextra310.so
hikyuu_plugin/pyextra311.so
hikyuu_plugin/pyextra312.so
hikyuu_plugin/pyextra313.so
hikyuu_plugin-2.7.3.dist-info/METADATA
hikyuu_plugin-2.7.3.dist-info/WHEEL
hikyuu_plugin-2.7.3.dist-info/top_level.txt
hikyuu_plugin-2.7.3.dist-info/RECORD
