Metadata-Version: 2.4
Name: hikyuu-plugin
Version: 2.7.3
Summary: Hikyuu Plugin Package
Home-page: https://github.com/fasiondog/hikyuu
Author: fasiondog
Author-email: fasiondog@gmail.com
License: LGPL-3.0-or-later
Classifier: Development Status :: 3 - Alpha
Classifier: Intended Audience :: Developers
Classifier: Operating System :: MacOS
Classifier: Operating System :: Microsoft :: Windows
Classifier: Operating System :: POSIX :: Linux
Classifier: Programming Language :: Python :: 3
Classifier: Programming Language :: Python :: 3.8
Classifier: Programming Language :: Python :: 3.9
Classifier: Programming Language :: Python :: 3.10
Classifier: Programming Language :: Python :: 3.11
Requires-Python: >=3.8
Dynamic: author
Dynamic: author-email
Dynamic: classifier
Dynamic: description
Dynamic: description-content-type
Dynamic: home-page
Dynamic: license
Dynamic: requires-python
Dynamic: summary
